genQC/__init__.py
genQC/_modidx.py
genQC/imports.py
genQC/benchmark/__init__.py
genQC/benchmark/bench_compilation.py
genQC/dataset/__init__.py
genQC/dataset/balancing.py
genQC/dataset/cached_dataset.py
genQC/dataset/circuits_dataset.py
genQC/dataset/config_dataset.py
genQC/dataset/dataset_helper.py
genQC/dataset/mixed_cached_dataset.py
genQC/inference/__init__.py
genQC/inference/eval_metrics.py
genQC/inference/evaluation_helper.py
genQC/inference/sampling.py
genQC/models/__init__.py
genQC/models/config_model.py
genQC/models/frozen_open_clip.py
genQC/models/layers.py
genQC/models/position_encoding.py
genQC/models/unet_qc.py
genQC/models/unitary_encoder.py
genQC/models/clip/__init__.py
genQC/models/clip/frozen_open_clip.py
genQC/models/clip/unitary_clip.py
genQC/models/embedding/__init__.py
genQC/models/embedding/base_embedder.py
genQC/models/embedding/rotational_preset_embedder.py
genQC/models/transformers/__init__.py
genQC/models/transformers/attention.py
genQC/models/transformers/cirdit_multimodal.py
genQC/models/transformers/transformers.py
genQC/pipeline/__init__.py
genQC/pipeline/callbacks.py
genQC/pipeline/compilation_diffusion_pipeline.py
genQC/pipeline/diffusion_pipeline.py
genQC/pipeline/diffusion_pipeline_special.py
genQC/pipeline/metrics.py
genQC/pipeline/multimodal_diffusion_pipeline.py
genQC/pipeline/pipeline.py
genQC/pipeline/unitary_clip_pipeline.py
genQC/platform/__init__.py
genQC/platform/circuits_generation.py
genQC/platform/circuits_instructions.py
genQC/platform/simulation.py
genQC/platform/backends/__init__.py
genQC/platform/backends/base_backend.py
genQC/platform/backends/circuits_cudaq.py
genQC/platform/backends/circuits_pennylane.py
genQC/platform/backends/circuits_qiskit.py
genQC/platform/tokenizer/__init__.py
genQC/platform/tokenizer/base_tokenizer.py
genQC/platform/tokenizer/circuits_tokenizer.py
genQC/platform/tokenizer/tensor_tokenizer.py
genQC/scheduler/__init__.py
genQC/scheduler/scheduler.py
genQC/scheduler/scheduler_ddim.py
genqc-0.2.3.dist-info/licenses/LICENSE.txt
genqc-0.2.3.dist-info/METADATA
genqc-0.2.3.dist-info/WHEEL
genqc-0.2.3.dist-info/entry_points.txt
genqc-0.2.3.dist-info/top_level.txt
genqc-0.2.3.dist-info/RECORD
