Metadata-Version: 2.4
Name: genQC
Version: 0.2.3
Summary: Generative quantum circuits
Home-page: https://github.com/FlorianFuerrutter/genQC
Author: Florian Fuerrutter
Author-email: f.fuerrutter@gmail.com
License: Apache Software License 2.0
Project-URL: Documentation, https://FlorianFuerrutter.github.io/genQC
Keywords: quantum-information diffusion-model generative-model
Classifier: Development Status :: 3 - Alpha
Classifier: Intended Audience :: Developers
Classifier: Natural Language :: English
Classifier: Programming Language :: Python :: 3.10
Classifier: Programming Language :: Python :: 3.12
Classifier: Programming Language :: Python :: 3.13
Classifier: License :: OSI Approved :: Apache Software License
Requires-Python: >=3.10
License-File: LICENSE.txt
Requires-Dist: packaging
Requires-Dist: torch
Requires-Dist: numpy
Requires-Dist: matplotlib
Requires-Dist: scipy
Requires-Dist: omegaconf
Requires-Dist: qiskit
Requires-Dist: tqdm
Requires-Dist: joblib
Requires-Dist: open_clip_torch
Requires-Dist: ipywidgets
Requires-Dist: pylatexenc
Requires-Dist: safetensors
Requires-Dist: tensordict
Requires-Dist: huggingface_hub
Provides-Extra: dev
Requires-Dist: jupyterlab; extra == "dev"
Requires-Dist: nbdev; extra == "dev"
Requires-Dist: cudaq; extra == "dev"
Requires-Dist: pennylane; extra == "dev"
Dynamic: author
Dynamic: author-email
Dynamic: classifier
Dynamic: description
Dynamic: description-content-type
Dynamic: home-page
Dynamic: keywords
Dynamic: license
Dynamic: license-file
Dynamic: project-url
Dynamic: provides-extra
Dynamic: requires-dist
Dynamic: requires-python
Dynamic: summary
